Workbook

Sheet Lead Log
A1: Week Of | B1: Date | C1: Lead Name | D1: Phone | E1: Company | F1: Prospect Type | G1: Source of Lead | H1: Campaign | I1: Lead ID | J1: Source of Referral | K1: Responded? | L1: Qualified? | M1: Reason Not Qualified | N1: Next Follow-up | O1: Notes
A2: =IF(B2="","",TEXT(B2-(WEEKDAY(B2,2)-1),"mmm d")&" - "&TEXT(B2-(WEEKDAY(B2,2)-1)+5,"mmm d")) -> Jun 29 - Jul 4 | B2: 46202 | C2: Habitations Durand | E2: Habitations Durand | F2: Developer | G2: Past Client/Contact | K2: No | O2: Bought land in St-Brigitte-de-Iberville from Ben Bouchard a prospecy; tried to reach, no answer.
A3: =IF(B3="","",TEXT(B3-(WEEKDAY(B3,2)-1),"mmm d")&" - "&TEXT(B3-(WEEKDAY(B3,2)-1)+5,"mmm d")) -> Jun 29 - Jul 4 | B3: 46202 | C3: Kitan Joshi | E3: BMO | F3: Banker | G3: COI Referral | J3: BMO: Karen Amar | K3: Yes | O3: COI; (OOTL).
A4: =IF(B4="","",TEXT(B4-(WEEKDAY(B4,2)-1),"mmm d")&" - "&TEXT(B4-(WEEKDAY(B4,2)-1)+5,"mmm d")) -> Jun 29 - Jul 4 | B4: 46202 | C4: Julia Huynh | E4: National Bank RE team | F4: Banker | G4: COI Referral | K4: Yes | O4: VP Associate, Real Estate Development Group.
A5: =IF(B5="","",TEXT(B5-(WEEKDAY(B5,2)-1),"mmm d")&" - "&TEXT(B5-(WEEKDAY(B5,2)-1)+5,"mmm d")) -> Jun 29 - Jul 4 | B5: 46202 | C5: Claudia Di Renzo | F5: Real Estate Broker | G5: Property Listing | K5: Yes | O5: Listed a 16-plex at 3175 Rue de Mont-Royal, Longueuil (Saint-Hubert). Already has a UW but open to exchanging coordinates.
A6: =IF(B6="","",TEXT(B6-(WEEKDAY(B6,2)-1),"mmm d")&" - "&TEXT(B6-(WEEKDAY(B6,2)-1)+5,"mmm d")) -> Jun 29 - Jul 4 | B6: 46202 | C6: Anthony Kyriacou | F6: Real Estate Broker | G6: COI Referral | J6: BDC | K6: No | O6: Has a client wanting to finance the 3600 St-Laurent building Odi old deal apparently client doesn’t want broker according to Odi
A7: =IF(B7="","",TEXT(B7-(WEEKDAY(B7,2)-1),"mmm d")&" - "&TEXT(B7-(WEEKDAY(B7,2)-1)+5,"mmm d")) -> Jun 29 - Jul 4 | B7: 46202 | C7: Ariane Beaudry | E7: GRH | F7: Other | K7: Yes | O7: Appraiser Muliti Res
A8: =IF(B8="","",TEXT(B8-(WEEKDAY(B8,2)-1),"mmm d")&" - "&TEXT(B8-(WEEKDAY(B8,2)-1)+5,"mmm d")) -> Jun 29 - Jul 4 | B8: 46203 | C8: Francis Lebel | E8: Investissement LeBel et Ouellet Inc. | F8: Investor | G8: Cold Outreach | K8: Yes | O8: Will send his 24-plex in Sainte-Anne-des-Plaines + 7x7 in Saint-Jerome.
A9: =IF(B9="","",TEXT(B9-(WEEKDAY(B9,2)-1),"mmm d")&" - "&TEXT(B9-(WEEKDAY(B9,2)-1)+5,"mmm d")) -> Jun 29 - Jul 4 | B9: 46203 | C9: Roberto Bellini | F9: Real Estate Broker | G9: LinkedIn | K9: Yes
A10: =IF(B10="","",TEXT(B10-(WEEKDAY(B10,2)-1),"mmm d")&" - "&TEXT(B10-(WEEKDAY(B10,2)-1)+5,"mmm d")) -> Jun 29 - Jul 4 | B10: 46203 | C10: Jeremie | D10: 438-490-1536 | E10: NXNE Capital | F10: Real Estate Broker | G10: Property Listing | K10: Yes | O10: Has a property for sale at 3462 Jeanne-Mance, Plateau-Mont-Royal O. 438 490-1536, also becoming a broker with his wife agreed to meet
A11: =IF(B11="","",TEXT(B11-(WEEKDAY(B11,2)-1),"mmm d")&" - "&TEXT(B11-(WEEKDAY(B11,2)-1)+5,"mmm d")) -> Jun 29 - Jul 4 | B11: 46203 | C11: Anna D. | F11: Real Estate Broker | G11: Cold Outreach | K11: Yes | O11: Reached out on IG; emailed her as follow-up.
A12: =IF(B12="","",TEXT(B12-(WEEKDAY(B12,2)-1),"mmm d")&" - "&TEXT(B12-(WEEKDAY(B12,2)-1)+5,"mmm d")) -> Jun 29 - Jul 4 | B12: 46204 | C12: Ben Bouchard | F12: Investor | G12: COI Referral | J12: RBC Deelvens team | K12: Yes | O12: Sold land to Habitations Durand; wants to buy the building he's renting in. benbouchard007@gmail.com
A13: =IF(B13="","",TEXT(B13-(WEEKDAY(B13,2)-1),"mmm d")&" - "&TEXT(B13-(WEEKDAY(B13,2)-1)+5,"mmm d")) -> Jun 29 - Jul 4 | B13: 46204 | C13: Sander Boelen | E13: Allegiant | F13: Investor | G13: COI Referral | J13: Alfredo Cosentino | K13: Yes | O13: OOTL; referred from a COI initial call
A14: =IF(B14="","",TEXT(B14-(WEEKDAY(B14,2)-1),"mmm d")&" - "&TEXT(B14-(WEEKDAY(B14,2)-1)+5,"mmm d")) -> Jun 29 - Jul 4 | B14: 46204 | C14: Karl Robert | F14: Real Estate Broker | G14: Property Listing | K14: Yes | O14: Property for sale at 750 Dupre, Beloeil. Willing to do a teaser. karl@karlrobert.com.
A15: =IF(B15="","",TEXT(B15-(WEEKDAY(B15,2)-1),"mmm d")&" - "&TEXT(B15-(WEEKDAY(B15,2)-1)+5,"mmm d")) -> Jun 29 - Jul 4 | B15: 46204 | C15: Shawn Giannone | F15: Real Estate Broker | G15: COI Referral | J15: Michael Martela | K15: Yes | O15: [1280 Douglas ] Operational broker; referred the Guzzo deal.
A16: =IF(B16="","",TEXT(B16-(WEEKDAY(B16,2)-1),"mmm d")&" - "&TEXT(B16-(WEEKDAY(B16,2)-1)+5,"mmm d")) -> Jun 29 - Jul 4 | B16: 46205 | C16: Mohamed Serraji | F16: Investor | G16: LinkedIn | K16: Yes | O16: Wants to buy a 6-plex.
A17: =IF(B17="","",TEXT(B17-(WEEKDAY(B17,2)-1),"mmm d")&" - "&TEXT(B17-(WEEKDAY(B17,2)-1)+5,"mmm d")) -> Jun 29 - Jul 4 | B17: 46205 | C17: Kokulan Chandren | F17: Real Estate Broker | G17: Other | K17: Yes | O17: Refered me stuff in the past didn’t close.
A18: =IF(B18="","",TEXT(B18-(WEEKDAY(B18,2)-1),"mmm d")&" - "&TEXT(B18-(WEEKDAY(B18,2)-1)+5,"mmm d")) -> Jun 29 - Jul 4 | B18: 46205 | C18: Joshua Bobrove | F18: Real Estate Broker | G18: Property Listing | K18: Yes | O18: Property for sale at 4120 Boul. des Grandes-Prairies.
A19: =IF(B19="","",TEXT(B19-(WEEKDAY(B19,2)-1),"mmm d")&" - "&TEXT(B19-(WEEKDAY(B19,2)-1)+5,"mmm d")) -> Jun 29 - Jul 4 | B19: 46205 | C19: Louis Palson | F19: Real Estate Broker | G19: Other | K19: No | O19: Land broker at Landerz - on vacation
A20: =IF(B20="","",TEXT(B20-(WEEKDAY(B20,2)-1),"mmm d")&" - "&TEXT(B20-(WEEKDAY(B20,2)-1)+5,"mmm d")) -> Jun 29 - Jul 4 | B20: 46206 | C20: Jean-Samuel Baillargeon | E20: TD | F20: Banker | G20: COI Referral | J20: National: Renaud Mondor | K20: Yes | O20: COI, reports directly under Elizabeth Roy.
A21: =IF(B21="","",TEXT(B21-(WEEKDAY(B21,2)-1),"mmm d")&" - "&TEXT(B21-(WEEKDAY(B21,2)-1)+5,"mmm d")) -> Jun 29 - Jul 4 | B21: 46206 | C21: Alexandre Lemieux | E21: Cosmo Group | F21: Other | G21: LinkedIn | K21: Yes | O21: COI; booked networking event tickets for August, going with Odi, bringing Colliers.
A22: =IF(B22="","",TEXT(B22-(WEEKDAY(B22,2)-1),"mmm d")&" - "&TEXT(B22-(WEEKDAY(B22,2)-1)+5,"mmm d")) -> Jun 29 - Jul 4 | B22: 46206 | C22: Ezat Wakil | F22: Investor | G22: COI Referral | J22: Michel Elias | K22: Yes | O22: Has a 4-plex, wants to add a floor to make it a 6-plex - Next year. Reach ut next year
A23: =IF(B23="","",TEXT(B23-(WEEKDAY(B23,2)-1),"mmm d")&" - "&TEXT(B23-(WEEKDAY(B23,2)-1)+5,"mmm d")) -> Jun 29 - Jul 4 | B23: 46206 | C23: Marie-Sophie.blanchet | E23: Scotia | F23: Banker | K23: Yes | O23: Marie-Sophie.blanchet@scotiabank.com CMGT approval team
A24: =IF(B24="","",TEXT(B24-(WEEKDAY(B24,2)-1),"mmm d")&" - "&TEXT(B24-(WEEKDAY(B24,2)-1)+5,"mmm d")) -> Jun 29 - Jul 4 | B24: 46206 | C24: Edgar Benoit | E24: Benoit Immo | F24: Property Manager | G24: COI Referral | J24: Arnau | K24: Yes | N24: 46220 | O24: Refered him Ridgewood asked him for referal
A25: =IF(B25="","",TEXT(B25-(WEEKDAY(B25,2)-1),"mmm d")&" - "&TEXT(B25-(WEEKDAY(B25,2)-1)+5,"mmm d")) -> Jul 6 - Jul 11 | B25: 46209 | C25: Veselka Naydenova | D25: 514-889-4972 | F25: Real Estate Broker | G25: Property Listing | K25: Yes | O25: Property at 2650 Avenue Barclay. 514 889-4972 - was very rude never to call again
A26: =IF(B26="","",TEXT(B26-(WEEKDAY(B26,2)-1),"mmm d")&" - "&TEXT(B26-(WEEKDAY(B26,2)-1)+5,"mmm d")) -> Jul 6 - Jul 11 | B26: 46209 | C26: Francois Mackay | D26: 514-637-9755 | F26: Real Estate Broker | G26: Property Listing | K26: No | O26: Property at 8781-8791 Avenue Henri-Julien, Montreal. 514 637-9755.
A27: =IF(B27="","",TEXT(B27-(WEEKDAY(B27,2)-1),"mmm d")&" - "&TEXT(B27-(WEEKDAY(B27,2)-1)+5,"mmm d")) -> Jul 6 - Jul 11 | B27: 46209 | C27: Nathalie Dore | D27: 418-929-4627 | F27: Real Estate Broker | G27: Property Listing | O27: Property at 2330-2340 Rue Bruneau, La Cite-Limoilou. 418 929-4627. Second listing - 1590 Avenue De Niverville, Quebec (La Cite-Limoilou).
A28: =IF(B28="","",TEXT(B28-(WEEKDAY(B28,2)-1),"mmm d")&" - "&TEXT(B28-(WEEKDAY(B28,2)-1)+5,"mmm d")) -> Jul 6 - Jul 11 | B28: 46209 | C28: Nathalie Dore | F28: Real Estate Broker | G28: Property Listing | K28: No | N28: 46219 | O28: Follow-up - 750 Dupre, Beloeil listing.
A29: =IF(B29="","",TEXT(B29-(WEEKDAY(B29,2)-1),"mmm d")&" - "&TEXT(B29-(WEEKDAY(B29,2)-1)+5,"mmm d")) -> Jul 6 - Jul 11 | B29: 46209 | C29: Ben Bouchard | F29: Investor | G29: Referral | K29: Yes | O29: Follow-up - wants to buy the building he's renting in at 149 Boul. Saint-Jean-Baptiste.
A30: =IF(B30="","",TEXT(B30-(WEEKDAY(B30,2)-1),"mmm d")&" - "&TEXT(B30-(WEEKDAY(B30,2)-1)+5,"mmm d")) -> Jul 6 - Jul 11 | B30: 46209 | C30: Jeremie | D30: 438-490-1536 | E30: NXNE Capital | F30: Real Estate Broker | G30: Property Listing | K30: Yes | N30: 46232 | O30: Has a property for sale at 3462 Jeanne-Mance, Plateau-Mont-Royal O. 438 490-1536, also becoming a broker with his wife agreed to meet
A31: =IF(B31="","",TEXT(B31-(WEEKDAY(B31,2)-1),"mmm d")&" - "&TEXT(B31-(WEEKDAY(B31,2)-1)+5,"mmm d")) -> Jul 6 - Jul 11 | B31: 46209 | C31: Karl Robert | F31: Real Estate Broker | G31: Property Listing | K31: No | N31: 46222 | O31: Property for sale at 750 Dupre, Beloeil. Willing to do a teaser. karl@karlrobert.com.
A32: =IF(B32="","",TEXT(B32-(WEEKDAY(B32,2)-1),"mmm d")&" - "&TEXT(B32-(WEEKDAY(B32,2)-1)+5,"mmm d")) -> Jul 6 - Jul 11 | B32: 46210 | C32: Jasmin Demers | D32: 450-521-6799 | F32: Real Estate Broker | G32: Property Listing | K32: Yes | N32: 46233 | O32: Property at 604-612 Avenue Sainte-Croix. 450 521-6799. Investor a la base, been 18 months hes a broker. Knows Jeff offered him to have coffee at our offices
A33: =IF(B33="","",TEXT(B33-(WEEKDAY(B33,2)-1),"mmm d")&" - "&TEXT(B33-(WEEKDAY(B33,2)-1)+5,"mmm d")) -> Jul 6 - Jul 11 | B33: 46210 | C33: Yanick Dionne | D33: 819-474-3134 | E33: Yanick Dionne Inc. | F33: Real Estate Broker | G33: Property Listing | O33: Property at 4870-4886 & 4890-4906 Rue Lagace, Drummondville. 819 474-3134.
A34: =IF(B34="","",TEXT(B34-(WEEKDAY(B34,2)-1),"mmm d")&" - "&TEXT(B34-(WEEKDAY(B34,2)-1)+5,"mmm d")) -> Jul 6 - Jul 11 | B34: 46210 | C34: Frank Iacobellis | D34: 450-704-0950 | F34: Investor | G34: Instagram Ad | K34: Yes | O34: Interested in CMHC programs. +1 450 704-0950, fiacobel@hotmail.com.
A35: =IF(B35="","",TEXT(B35-(WEEKDAY(B35,2)-1),"mmm d")&" - "&TEXT(B35-(WEEKDAY(B35,2)-1)+5,"mmm d")) -> Jul 6 - Jul 11 | B35: 46210 | C35: Joshua Bobrove | F35: Real Estate Broker | G35: Property Listing | K35: Yes | N35: 46223 | O35: [Sent prelim UW] Property for sale at 4120 Boul. des Grandes-Prairies; sent me the #s for UW
A36: =IF(B36="","",TEXT(B36-(WEEKDAY(B36,2)-1),"mmm d")&" - "&TEXT(B36-(WEEKDAY(B36,2)-1)+5,"mmm d")) -> Jul 6 - Jul 11 | B36: 46210 | C36: Laurent Suissa | E36: RCGT | F36: Lawyer | G36: COI Referral | K36: Yes | O36: Tax lawyer; 80% of his portfolio is real estate (COI).
A37: =IF(B37="","",TEXT(B37-(WEEKDAY(B37,2)-1),"mmm d")&" - "&TEXT(B37-(WEEKDAY(B37,2)-1)+5,"mmm d")) -> Jul 6 - Jul 11 | B37: 46211 | C37: Danny Cormier | F37: Real Estate Broker | G37: Property Listing | K37: Yes | N37: 46219 | O37: Property at 25 Rue Saint-Joseph. PMML already engaged on this one. Spoke to his collegue Pierre Luc 819 350-9955 'plstonge@remax-elite.ca'
A38: =IF(B38="","",TEXT(B38-(WEEKDAY(B38,2)-1),"mmm d")&" - "&TEXT(B38-(WEEKDAY(B38,2)-1)+5,"mmm d")) -> Jul 6 - Jul 11 | B38: 46211 | C38: Simon Beausejour / Yvon Cousineau | D38: 450-898-3113 | F38: Real Estate Broker | G38: Property Listing | K38: Yes | O38: Property at 2763 Rue Monette. 450 898-3113. https://sutton-synergie.ca/ - They cover Joliette, Repentigny, Montreal, Saint-Eustache, Saint-Donat, Saint-Sauveur, and Saint-Jérôme. Spoke to Sonia secretary: Bunch that are commercial; Simon, Martin Remi, Mr cloutier, Covac, Julie
A39: =IF(B39="","",TEXT(B39-(WEEKDAY(B39,2)-1),"mmm d")&" - "&TEXT(B39-(WEEKDAY(B39,2)-1)+5,"mmm d")) -> Jul 6 - Jul 11 | B39: 46211 | C39: M. Chev | D39: 514-578-7366 | E39: Art Refinancing | F39: Investor | G39: Instagram Ad | K39: No | N39: 46219 | O39: Refinancing inquiry. +1 514 578-7366, m.chev_fineart@hotmail.ca.
A40: =IF(B40="","",TEXT(B40-(WEEKDAY(B40,2)-1),"mmm d")&" - "&TEXT(B40-(WEEKDAY(B40,2)-1)+5,"mmm d")) -> Jul 6 - Jul 11 | B40: 46211 | C40: Jeremie | E40: NXNE Capital | F40: Real Estate Broker | G40: Property Listing | K40: Yes | O40: Follow-up - 3462 Jeanne-Mance, Plateau-Mont-Royal O listing.
A41: =IF(B41="","",TEXT(B41-(WEEKDAY(B41,2)-1),"mmm d")&" - "&TEXT(B41-(WEEKDAY(B41,2)-1)+5,"mmm d")) -> Jul 6 - Jul 11 | B41: 46211 | C41: Gilad Ben Dor | E41: National Bank (BNC) | F41: Banker | G41: COI Referral | K41: Yes | O41: National Bank real estate team (COI).
A42: =IF(B42="","",TEXT(B42-(WEEKDAY(B42,2)-1),"mmm d")&" - "&TEXT(B42-(WEEKDAY(B42,2)-1)+5,"mmm d")) -> Jul 6 - Jul 11 | B42: 46211 | C42: Chloee Chamberland | E42: Imso | F42: Investor | G42: Networking Event | K42: Yes | O42: [1400 Marie-Victorin, St-Bruno] 2 commercial buildings + 1 assumation
A43: =IF(B43="","",TEXT(B43-(WEEKDAY(B43,2)-1),"mmm d")&" - "&TEXT(B43-(WEEKDAY(B43,2)-1)+5,"mmm d")) -> Jul 6 - Jul 11 | B43: 46212 | C43: Jacinthe Parenteau | D43: 514-968-9961 | F43: Real Estate Broker | G43: Property Listing | K43: Yes | O43: Property at 142 Rue Notre-Dame, Notre-Dame-du-Bon-Conseil. 514 968-9961. parenteau.filles@remax-quebec.com She said: Already have direct contacts with banks; told her market changes and I used to work there. She told me a lot of her clients have a lot of doors and know the ropes; yes but changes with CMHC, plus we do 3 billion of transactions so we have those type of clients and its even more experience on how to position files
A44: =IF(B44="","",TEXT(B44-(WEEKDAY(B44,2)-1),"mmm d")&" - "&TEXT(B44-(WEEKDAY(B44,2)-1)+5,"mmm d")) -> Jul 6 - Jul 11 | B44: 46212 | C44: Tony Vinado Douk | D44: 514-431-4315 | F44: Real Estate Broker | G44: Property Listing | K44: Yes | O44: Property at 2095 Boul. Grand, Montreal. Owners: Kevinnick Pong, Rith Kang, Thakounthap Pong, Eddyrick Pong. 514 431-4315 His brother works at ICI Canada, Jeremie Douk CPA, started a year ago. Clietn clients are childood friend mostly chinese already have a broker, didnt refer to his brother yet.
A45: =IF(B45="","",TEXT(B45-(WEEKDAY(B45,2)-1),"mmm d")&" - "&TEXT(B45-(WEEKDAY(B45,2)-1)+5,"mmm d")) -> Jul 6 - Jul 11 | B45: 46212 | C45: Robert Glode | D45: 514-772-2358 | F45: Developer | G45: Instagram Ad | K45: Yes | O45: Built a 16-plex in Saint-Jean-sur-Richelieu, wants to build two more; Desjardins has no more money to lend. 514 772-2358, robertglode@hotmail.com.
A46: =IF(B46="","",TEXT(B46-(WEEKDAY(B46,2)-1),"mmm d")&" - "&TEXT(B46-(WEEKDAY(B46,2)-1)+5,"mmm d")) -> Jul 6 - Jul 11 | B46: 46212 | C46: Vincent Chenier | D46: 514-609-8269 | F46: Investor | G46: Instagram Ad | K46: Yes | O46: Refinancing - 27 Rue de l'Eglise, Edmundston NB; 40-unit property, $2.6M. 514 609-8269, vincent.chenier3@gmail.com.
A47: =IF(B47="","",TEXT(B47-(WEEKDAY(B47,2)-1),"mmm d")&" - "&TEXT(B47-(WEEKDAY(B47,2)-1)+5,"mmm d")) -> Jul 6 - Jul 11 | B47: 46212 | C47: Anna D. | F47: Real Estate Broker | G47: Cold Outreach | K47: No | O47: Follow-up email after IG outreach.
A48: =IF(B48="","",TEXT(B48-(WEEKDAY(B48,2)-1),"mmm d")&" - "&TEXT(B48-(WEEKDAY(B48,2)-1)+5,"mmm d")) -> Jul 6 - Jul 11 | B48: 46212 | C48: Julia Huynh | E48: National Bank (BNC) | F48: Banker | G48: COI Referral | K48: Yes | O48: Follow-up, National Bank real estate team (COI).
A49: =IF(B49="","",TEXT(B49-(WEEKDAY(B49,2)-1),"mmm d")&" - "&TEXT(B49-(WEEKDAY(B49,2)-1)+5,"mmm d")) -> Jul 6 - Jul 11 | B49: 46212 | C49: Sander Boelen | E49: Allegiant | F49: Investor | G49: COI Referral | J49: Alfredo Cosentino | K49: Yes | O49: F/U business owner wants to buy a property wants to know his budget F/U to get his NDA signed so I can get the FS
A50: =IF(B50="","",TEXT(B50-(WEEKDAY(B50,2)-1),"mmm d")&" - "&TEXT(B50-(WEEKDAY(B50,2)-1)+5,"mmm d")) -> Jul 6 - Jul 11 | B50: 46212 | C50: Kokulan | F50: Real Estate Broker | G50: Other | K50: Yes | O50: Refered me stuff in the past didn’t close.
A51: =IF(B51="","",TEXT(B51-(WEEKDAY(B51,2)-1),"mmm d")&" - "&TEXT(B51-(WEEKDAY(B51,2)-1)+5,"mmm d")) -> Jul 6 - Jul 11 | B51: 46213 | C51: Paul Parenteau | D51: 819-470-0240 | F51: Real Estate Broker | G51: Property Listing | O51: Co-broker on 142 Rue Notre-Dame, Notre-Dame-du-Bon-Conseil. 819 470-0240.
A52: =IF(B52="","",TEXT(B52-(WEEKDAY(B52,2)-1),"mmm d")&" - "&TEXT(B52-(WEEKDAY(B52,2)-1)+5,"mmm d")) -> Jul 6 - Jul 11 | B52: 46213 | C52: Saguy Elbaz | D52: 514-892-7653 / 514-612-6892 | F52: Real Estate Broker | G52: Property Listing | O52: Property at 2265 Avenue Madison. Owners: Philip Kakon, Eric Wazana, Yacov Wazana. 514 892-7653 / 514 612-6892.
A53: =IF(B53="","",TEXT(B53-(WEEKDAY(B53,2)-1),"mmm d")&" - "&TEXT(B53-(WEEKDAY(B53,2)-1)+5,"mmm d")) -> Jul 6 - Jul 11 | B53: 46213 | C53: Joe Turturici | D53: 514-757-1973 | F53: Investor | G53: Instagram Ad | K53: Yes | N53: 46223 | O53: Has a conventional 7-plex, plus 2x12-plex with a group; wants to leverage with CMHC. 514 757-1973, joe.t@turpone.com.
A54: =IF(B54="","",TEXT(B54-(WEEKDAY(B54,2)-1),"mmm d")&" - "&TEXT(B54-(WEEKDAY(B54,2)-1)+5,"mmm d")) -> Jul 6 - Jul 11 | B54: 46213 | C54: Siva Vaitheeswaran | D54: 514-923-7907 | F54: Investor | G54: Instagram Ad | K54: Yes | O54: Interested in CMHC programs. +1 514 923-7907, v_siva45@hotmail.com.
A55: =IF(B55="","",TEXT(B55-(WEEKDAY(B55,2)-1),"mmm d")&" - "&TEXT(B55-(WEEKDAY(B55,2)-1)+5,"mmm d")) -> Jul 6 - Jul 11 | B55: 46213 | C55: Francis Lebel | F55: Investor | G55: Cold Outreach | K55: Yes | N55: 46221 | O55: Follow-up - 24-plex Sainte-Anne-des-Plaines + 7x7 Saint-Jerome Said he will send me everything next week
A56: =IF(B56="","",TEXT(B56-(WEEKDAY(B56,2)-1),"mmm d")&" - "&TEXT(B56-(WEEKDAY(B56,2)-1)+5,"mmm d")) -> Jul 13 - Jul 18 | B56: 46216 | C56: Amandip-Singh Dhaliwal | D56: 438-889-8863 / 514-426-0047 | F56: Real Estate Broker | G56: Property Listing | O56: Has a triplex on Keller; call regardless. 438 889-8863 / 514 426-0047.
A57: =IF(B57="","",TEXT(B57-(WEEKDAY(B57,2)-1),"mmm d")&" - "&TEXT(B57-(WEEKDAY(B57,2)-1)+5,"mmm d")) -> Jul 13 - Jul 18 | B57: 46216 | C57: Carmine Padula | D57: 514-360-8480 | F57: Real Estate Broker | G57: Property Listing | O57: Property at 7001 Rue Jarry Est, Montreal (Anjou). 514 360-8480.
A58: =IF(B58="","",TEXT(B58-(WEEKDAY(B58,2)-1),"mmm d")&" - "&TEXT(B58-(WEEKDAY(B58,2)-1)+5,"mmm d")) -> Jul 13 - Jul 18 | B58: 46216 | C58: Amy Assad | D58: 514-884-8000 | F58: Real Estate Broker | G58: Property Listing | O58: Multiple Ville-Marie addresses (419-427 Avenue Viger Est; 698-704 & 350-350A Rue Notre-Dame). Owner: Emile H. Benamor. 514 884-8000.
A59: =IF(B59="","",TEXT(B59-(WEEKDAY(B59,2)-1),"mmm d")&" - "&TEXT(B59-(WEEKDAY(B59,2)-1)+5,"mmm d")) -> Jul 13 - Jul 18 | B59: 46216 | C59: Claude Lessard | D59: 514-386-6176 / 450-661-6810 | F59: Real Estate Broker | G59: Property Listing | O59: Property at 80 Place Mercier, Candiac. 514 386-6176 / 450 661-6810.
A60: =IF(B60="","",TEXT(B60-(WEEKDAY(B60,2)-1),"mmm d")&" - "&TEXT(B60-(WEEKDAY(B60,2)-1)+5,"mmm d")) -> Jul 13 - Jul 18 | B60: 46216 | C60: Marie-Christine Pelletier | F60: Real Estate Broker | G60: Property Listing | O60: Property at 7496-7502 Avenue Christophe-Colomb. Owners: Isabelle Cote & Terry Alieu. 514 8262-7631.
A61: =IF(B61="","",TEXT(B61-(WEEKDAY(B61,2)-1),"mmm d")&" - "&TEXT(B61-(WEEKDAY(B61,2)-1)+5,"mmm d")) -> Jul 13 - Jul 18 | B61: 46216 | C61: Alex Samson | D61: 514-984-1658 / 450-692-1090 | F61: Real Estate Broker | G61: Property Listing | O61: Property at 818 Boul. Saint-Jean-Baptiste. 514 984-1658 / 450 692-1090.
A62: =IF(B62="","",TEXT(B62-(WEEKDAY(B62,2)-1),"mmm d")&" - "&TEXT(B62-(WEEKDAY(B62,2)-1)+5,"mmm d")) -> Jul 13 - Jul 18 | B62: 46216 | C62: Charles Antoine Lalonde | E62: Account manager @ Graitec Canada | F62: Other | G62: LinkedIn | K62: Yes
A63: =IF(B63="","",TEXT(B63-(WEEKDAY(B63,2)-1),"mmm d")&" - "&TEXT(B63-(WEEKDAY(B63,2)-1)+5,"mmm d")) -> Jul 13 - Jul 18 | B63: 46216 | C63: Caroline Einish | D63: 418-585-2770 | F63: Investor | G63: Instagram Ad | K63: Yes | O63: 418 585-2770 einishcaroline@gmail.com - Luc, old guy, answered call back later to speak to Caroline hes not aware of anything ..
A64: =IF(B64="","",TEXT(B64-(WEEKDAY(B64,2)-1),"mmm d")&" - "&TEXT(B64-(WEEKDAY(B64,2)-1)+5,"mmm d")) -> Jul 13 - Jul 18 | B64: 46216 | C64: Christopher Piedad | D64: 418-409-6873 | F64: Investor | G64: Instagram Ad | K64: No | O64: 418 409 6873 topietops@yahoo.com
A65: =IF(B65="","",TEXT(B65-(WEEKDAY(B65,2)-1),"mmm d")&" - "&TEXT(B65-(WEEKDAY(B65,2)-1)+5,"mmm d")) -> Jul 13 - Jul 18 | B65: 46216 | C65: Khalil Tabatabai | D65: 514-968-5991 | F65: Investor | G65: Instagram Ad | K65: Yes | O65: 514 968-5991 Khalil Tabatabai has a 3 plex in montreal and 2 plex in Windsow, and a islamic school in Windsor with land next to it wants to build 100 units . Zero experience
A66: =IF(B66="","",TEXT(B66-(WEEKDAY(B66,2)-1),"mmm d")&" - "&TEXT(B66-(WEEKDAY(B66,2)-1)+5,"mmm d")) -> Jul 13 - Jul 18 | B66: 46216 | C66: Marie-Sophie.blanchet@scotiabank.com | F66: Banker | G66: COI Referral | K66: Yes | O66: Teams meeting; shes the one in charge of the Scotia files
A67: =IF(B67="","",TEXT(B67-(WEEKDAY(B67,2)-1),"mmm d")&" - "&TEXT(B67-(WEEKDAY(B67,2)-1)+5,"mmm d")) -> Jul 13 - Jul 18 | B67: 46217 | C67: Emily Donahue | E67: De Grandpre Chait | F67: Lawyer | G67: Networking Event | K67: Yes | O67: Invited me to Soccer Game Thursday
A68: =IF(B68="","",TEXT(B68-(WEEKDAY(B68,2)-1),"mmm d")&" - "&TEXT(B68-(WEEKDAY(B68,2)-1)+5,"mmm d")) -> Jul 13 - Jul 18 | B68: 46217 | C68: Amine Guénnich | E68: RBC | F68: Banker | G68: Other | K68: Yes | O68: [1335 BOUL SAINTE-CATHERINE & 1493-1499 ATATEKEN ] Senior Financing Specialist now. Reached out because he has a client looking to refinance two semi-commercial buildings in downtown Montreal, currently financed with RBC. CAM:Guillaume De Tillidon, Owner of an adult production company and Le Campus Village. Reviewed his real estate portfolio, including an owner-occupied mixed-use property on Ste-Catherine (office, basement unit and two residential condos, approx. $1.4M mortgage balance) and an 8–10-unit property on Atateken with one commercial tenant (laundromat/hairdresser, est. value $1.1M). Relationship was escalated after requests for a line of credit, Visa and GRM, as total exposure exceeded $3M, triggering an annual CAG review. Main discussion focused on compliance/PSOA considerations and the business's relatively tight cash flow due to ongoing production-related expenses and investments.
A69: =IF(B69="","",TEXT(B69-(WEEKDAY(B69,2)-1),"mmm d")&" - "&TEXT(B69-(WEEKDAY(B69,2)-1)+5,"mmm d")) -> Jul 13 - Jul 18 | B69: 46217 | C69: Olivier Lepine | E69: RBC | F69: Banker | K69: Yes | O69: Real Estate Group; IMSO
A70: =IF(B70="","",TEXT(B70-(WEEKDAY(B70,2)-1),"mmm d")&" - "&TEXT(B70-(WEEKDAY(B70,2)-1)+5,"mmm d")) -> Jul 13 - Jul 18 | B70: 46217 | C70: Lucas | E70: Canora Team | F70: Investor | G70: Property Listing | K70: Yes | O70: Mathieu is friendly with Jeffrey.Charles (founder) appreciates the offer but theyre well served already in term so financing!
A71: =IF(B71="","",TEXT(B71-(WEEKDAY(B71,2)-1),"mmm d")&" - "&TEXT(B71-(WEEKDAY(B71,2)-1)+5,"mmm d")) -> Jul 13 - Jul 18 | B71: 46217 | C71: Bassel Abboud | E71: Cushman | F71: Other | G71: LinkedIn | K71: Yes | O71: [6700 Boul Laurier] I have a client who is looking to buy a gas station. They have a down payment between 200-250k. - not double wall tank and not enough down.. We are 100k short. Purchase price was 945k
A72: =IF(B72="","",TEXT(B72-(WEEKDAY(B72,2)-1),"mmm d")&" - "&TEXT(B72-(WEEKDAY(B72,2)-1)+5,"mmm d")) -> Jul 13 - Jul 18 | B72: 46218 | C72: Oren Elbaz | K72: No
A73: =IF(B73="","",TEXT(B73-(WEEKDAY(B73,2)-1),"mmm d")&" - "&TEXT(B73-(WEEKDAY(B73,2)-1)+5,"mmm d")) -> Jul 13 - Jul 18 | B73: 46218 | C73: Sarah Adam | G73: Instagram Ad | K73: Yes | O73: Mikeadam809@gmail.com - has land in laval (85 Rue Grenon E) with a carrosserie on it - 20 apparments - 3 floors or sell it.. Or build something a carrosserie on land he wants to buy. No experience.
A74: =IF(B74="","",TEXT(B74-(WEEKDAY(B74,2)-1),"mmm d")&" - "&TEXT(B74-(WEEKDAY(B74,2)-1)+5,"mmm d")) -> Jul 13 - Jul 18 | B74: 46218 | C74: Guillaume Patenaude | G74: COI Referral | J74: Amine G. RBC | K74: Yes
A75: =IF(B75="","",TEXT(B75-(WEEKDAY(B75,2)-1),"mmm d")&" - "&TEXT(B75-(WEEKDAY(B75,2)-1)+5,"mmm d")) -> Jul 13 - Jul 18 | B75: 46218 | C75: Mohamed Yacoub | D75: 514-781-5129 | F75: Investor | G75: COI Referral | J75: Usman | K75: Yes | N75: 46223 | O75: [Verdun 6 porte] 514-781-5129 <myacoub888@gmail.com> Project in Verdun has land did some plans can build 6 or 8 units.. Told him to send me his budget and unit mix when hes ready
A76: =IF(B76="","",TEXT(B76-(WEEKDAY(B76,2)-1),"mmm d")&" - "&TEXT(B76-(WEEKDAY(B76,2)-1)+5,"mmm d")) -> Jul 13 - Jul 18 | B76: 46218 | C76: Cédric Dagenais | E76: PWC | F76: Accountant | K76: Yes | O76: Emailed him asked if he worked on the 6600 Saint-Urbain, that just closed with Laurentienne Olymbec fro PWC Restructuring team. Asked for a catch up call.
A77: =IF(B77="","",TEXT(B77-(WEEKDAY(B77,2)-1),"mmm d")&" - "&TEXT(B77-(WEEKDAY(B77,2)-1)+5,"mmm d")) -> Jul 13 - Jul 18 | B77: 46218 | C77: Alfredo | E77: Marcus Milichp | F77: Real Estate Broker | K77: Yes | O77: [Sander Boeng] Refered me a client looking to buy an owner occupied buildign for his operations. We are trying to see how he can refer me more and how hes getting his leads
A78: =IF(B78="","",TEXT(B78-(WEEKDAY(B78,2)-1),"mmm d")&" - "&TEXT(B78-(WEEKDAY(B78,2)-1)+5,"mmm d")) -> Jul 13 - Jul 18 | B78: 46219 | C78: Dominique Daigle | E78: Agile Solutions | F78: Other | K78: Yes | O78: [227 boul. Saint Maurice] Dom is an operational broker at Agile Solution, has a client buying the business + building (trois riviere). PP 13.3M Evaluation at 18.6M but avec bcp denjeux environemntal bc it’s a manufacturing company that has iron contamination. Business has been there for over 50 years
A79: =IF(B79="","",TEXT(B79-(WEEKDAY(B79,2)-1),"mmm d")&" - "&TEXT(B79-(WEEKDAY(B79,2)-1)+5,"mmm d")) -> Jul 13 - Jul 18 | B79: 46219 | C79: Kokulan | K79: Yes | O79: [6444-6490 Avenue Victoria] Has a lien on the property 475k- wants to build 8 residential units
A80: =IF(B80="","",TEXT(B80-(WEEKDAY(B80,2)-1),"mmm d")&" - "&TEXT(B80-(WEEKDAY(B80,2)-1)+5,"mmm d")) -> Jul 13 - Jul 18 | B80: 46219 | C80: Alexandre Provost Ing | E80: Trane Technologies | F80: Investor | G80: Networking Event | K80: Yes | N80: 46223 | O80: Circle 13; has a potential project in the outskirts of montreal a piece of land next to a hospital I believe able to build 100 units
A81: =IF(B81="","",TEXT(B81-(WEEKDAY(B81,2)-1),"mmm d")&" - "&TEXT(B81-(WEEKDAY(B81,2)-1)+5,"mmm d")) -> Jul 13 - Jul 18 | B81: 46219 | C81: Massimo Paolitto | E81: Masscon | F81: Developer | G81: Networking Event | K81: Yes | O81: Circle 13; was supposed to have coffee with Jeff is traveling until end of August will be back
A82: =IF(B82="","",TEXT(B82-(WEEKDAY(B82,2)-1),"mmm d")&" - "&TEXT(B82-(WEEKDAY(B82,2)-1)+5,"mmm d")) -> Jul 13 - Jul 18 | B82: 46219 | C82: Francis Lavigne | E82: Groupe Jesta | F82: Developer | G82: Networking Event | K82: Yes | O82: Circle 13; Responsible de la construction de project
A83: =IF(B83="","",TEXT(B83-(WEEKDAY(B83,2)-1),"mmm d")&" - "&TEXT(B83-(WEEKDAY(B83,2)-1)+5,"mmm d")) -> Jul 13 - Jul 18 | B83: 46219 | C83: Joe Argento | F83: Developer | G83: Networking Event | K83: Yes | O83: Circle 13; catching up
A84: =IF(B84="","",TEXT(B84-(WEEKDAY(B84,2)-1),"mmm d")&" - "&TEXT(B84-(WEEKDAY(B84,2)-1)+5,"mmm d")) -> Jul 13 - Jul 18 | B84: 46219 | C84: Peter Morris | F84: Other | G84: Networking Event | K84: Yes | O84: Circle 13; breif introduction
A85: =IF(B85="","",TEXT(B85-(WEEKDAY(B85,2)-1),"mmm d")&" - "&TEXT(B85-(WEEKDAY(B85,2)-1)+5,"mmm d")) -> Jul 13 - Jul 18 | B85: 46219 | C85: Valerie Goulet | E85: Humanscale | F85: Other | G85: Networking Event | K85: Yes | N85: 46223 | O85: Circle 13; potential prospecting meeting. She reaches out to developers and does ergonomic assessments for their tenants
A86: =IF(B86="","",TEXT(B86-(WEEKDAY(B86,2)-1),"mmm d")&" - "&TEXT(B86-(WEEKDAY(B86,2)-1)+5,"mmm d")) -> Jul 13 - Jul 18 | B86: 46219 | C86: Benjamin Gauld | E86: Royal Lepage | F86: Real Estate Broker | G86: Networking Event | K86: Yes | O86: Circle 13; seems like he had hot leads for me, does only commercial
A87: =IF(B87="","",TEXT(B87-(WEEKDAY(B87,2)-1),"mmm d")&" - "&TEXT(B87-(WEEKDAY(B87,2)-1)+5,"mmm d")) -> Jul 13 - Jul 18 | B87: 46219 | C87: Brigitte Dupuis | E87: GBI | G87: Networking Event | K87: Yes | O87: Circle 13; bought her book (engineering firm)
A88: =IF(B88="","",TEXT(B88-(WEEKDAY(B88,2)-1),"mmm d")&" - "&TEXT(B88-(WEEKDAY(B88,2)-1)+5,"mmm d")) -> Jul 13 - Jul 18 | B88: 46219 | C88: Jean-Bernard Parenteau | E88: Borealis - Appraiser | F88: Other | G88: Networking Event | K88: Yes | O88: Circle 13; hes the head of Circle 13 but also we caught up we had spoken a while back regarding my hotel deal he actually remmebered
A89: =IF(B89="","",TEXT(B89-(WEEKDAY(B89,2)-1),"mmm d")&" - "&TEXT(B89-(WEEKDAY(B89,2)-1)+5,"mmm d")) -> Jul 20 - Jul 25 | B89: 46223 | C89: Ralph Karawani | E89: Equans Services Inc. | G89: Networking Event | K89: Yes | O89: Circle 13; Building operations and energy services
A90: =IF(B90="","",TEXT(B90-(WEEKDAY(B90,2)-1),"mmm d")&" - "&TEXT(B90-(WEEKDAY(B90,2)-1)+5,"mmm d")) -> Jul 20 - Jul 25 | B90: 46223 | C90: Martin Bernier Belanger | E90: Strata - Enviro | G90: Networking Event | K90: Yes | O90: Circle 13; ESA Report
A91: =IF(B91="","",TEXT(B91-(WEEKDAY(B91,2)-1),"mmm d")&" - "&TEXT(B91-(WEEKDAY(B91,2)-1)+5,"mmm d")) -> Jul 20 - Jul 25 | B91: 46223 | C91: Robert Glode | D91: 514-772-2358 | F91: Developer | K91: Yes | O91: Built a 16-plex in Saint-Jean-sur-Richelieu, wants to build two more; rented first phase deja. Desjardins has no more money to lend. 514 772-2358, robertglode@hotmail.com.
A92: =IF(B92="","",TEXT(B92-(WEEKDAY(B92,2)-1),"mmm d")&" - "&TEXT(B92-(WEEKDAY(B92,2)-1)+5,"mmm d")) -> Jul 20 - Jul 25 | B92: 46223 | C92: Fiona Chang | E92: Avison Young | F92: Real Estate Broker | K92: Yes | O92: Works with Gad and Shlomo- spoek to me about Zoominfo to look into to get contact info but mostly works for businesses..
A93: =IF(B93="","",TEXT(B93-(WEEKDAY(B93,2)-1),"mmm d")&" - "&TEXT(B93-(WEEKDAY(B93,2)-1)+5,"mmm d")) -> Jul 20 - Jul 25 | B93: 46223 | C93: Mourad Bouhaddi | E93: Avea | F93: Investor | K93: Yes | O93: Has a 21 door + 6 door for sale. I sent it to a bunch of people I thought could be interested or know someone. Joe Argento, Ulric, Francis Lebel, Francis Beauregard, Peter Halaby, RBC
A94: =IF(B94="","",TEXT(B94-(WEEKDAY(B94,2)-1),"mmm d")&" - "&TEXT(B94-(WEEKDAY(B94,2)-1)+5,"mmm d")) -> Jul 20 - Jul 25 | B94: 46225 | C94: Robert Glode | F94: Developer | K94: Yes | O94: Follow up by email and call to get construction budget or something
A95: =IF(B95="","",TEXT(B95-(WEEKDAY(B95,2)-1),"mmm d")&" - "&TEXT(B95-(WEEKDAY(B95,2)-1)+5,"mmm d")) -> Jul 20 - Jul 25 | B95: 46225 | C95: David Dayan | E95: National Bank (BNC) | F95: Banker | K95: Yes | O95: Real Estate team
A96: =IF(B96="","",TEXT(B96-(WEEKDAY(B96,2)-1),"mmm d")&" - "&TEXT(B96-(WEEKDAY(B96,2)-1)+5,"mmm d")) -> Jul 20 - Jul 25 | B96: 46225 | C96: Anthony D'Andrea | E96: TD | F96: Banker | K96: Yes | O96: Does investment properties and OOTL D'Andrea, Anthony M <Anthony.D'Andrea@td.com>
A97: =IF(B97="","",TEXT(B97-(WEEKDAY(B97,2)-1),"mmm d")&" - "&TEXT(B97-(WEEKDAY(B97,2)-1)+5,"mmm d")) -> Jul 20 - Jul 25 | B97: 46225 | C97: Andrea Piccolo | E97: Immotec | F97: Developer | K97: Yes | O97: Follow up on grabbing lunch
A98: =IF(B98="","",TEXT(B98-(WEEKDAY(B98,2)-1),"mmm d")&" - "&TEXT(B98-(WEEKDAY(B98,2)-1)+5,"mmm d")) -> Jul 20 - Jul 25 | B98: 46225 | C98: Anh Tan | E98: IQ | F98: Banker | K98: Yes | O98: Follow up
A99: =IF(B99="","",TEXT(B99-(WEEKDAY(B99,2)-1),"mmm d")&" - "&TEXT(B99-(WEEKDAY(B99,2)-1)+5,"mmm d")) -> Jul 20 - Jul 25 | B99: 46225 | C99: Jean-Paul Pham | E99: Laurentienne | F99: Banker | K99: Yes | O99: Laurentienne appetite quarterly check
A100: =IF(B100="","",TEXT(B100-(WEEKDAY(B100,2)-1),"mmm d")&" - "&TEXT(B100-(WEEKDAY(B100,2)-1)+5,"mmm d")) -> Jul 20 - Jul 25 | B100: 46225 | C100: Saad Shaikh | F100: Investor | K100: Yes
...

Sheet Weekly Summary
A1: WEEKLY PIPELINE MEETING SUMMARY
A2: Weekly target (leads responded): | C2: 25
A4: Week Of | B4: Leads Contacted | C4: Responded | D4: Response Rate | E4: Target Met?
A5: Jun 29 - Jul 4 | B5: =COUNTIF('Lead Log'!$A:$A,A5) -> 23 | C5: =COUNTIFS('Lead Log'!$A:$A,A5,'Lead Log'!$K:$K,"Yes") -> 20 | D5: =IFERROR(C5/B5,0) -> 0.86956522 | E5: =IF(C5>=$C$2,"Yes","No") -> No
A6: Jul 6 - Jul 11 | B6: =COUNTIF('Lead Log'!$A:$A,A6) -> 31 | C6: =COUNTIFS('Lead Log'!$A:$A,A6,'Lead Log'!$K:$K,"Yes") -> 22 | D6: =IFERROR(C6/B6,0) -> 0.70967742 | E6: =IF(C6>=$C$2,"Yes","No") -> No
A7: Jul 13 - Jul 18 | B7: =COUNTIF('Lead Log'!$A:$A,A7) -> 33 | C7: =COUNTIFS('Lead Log'!$A:$A,A7,'Lead Log'!$K:$K,"Yes") -> 25 | D7: =IFERROR(C7/B7,0) -> 0.75757576 | E7: =IF(C7>=$C$2,"Yes","No") -> Yes
A8: Jul 20 - Jul 25 | B8: =COUNTIF('Lead Log'!$A:$A,A8) -> 12 | C8: =COUNTIFS('Lead Log'!$A:$A,A8,'Lead Log'!$K:$K,"Yes") -> 12 | D8: =IFERROR(C8/B8,0) -> 1 | E8: =IF(C8>=$C$2,"Yes","No") -> No
A9: Jul 27 - Aug 1 | B9: =COUNTIF('Lead Log'!$A:$A,A9) -> 17 | C9: =COUNTIFS('Lead Log'!$A:$A,A9,'Lead Log'!$K:$K,"Yes") -> 17 | D9: =IFERROR(C9/B9,0) -> 1 | E9: =IF(C9>=$C$2,"Yes","No") -> No
A10: Aug 3 - Aug 8 | B10: =COUNTIF('Lead Log'!$A:$A,A10) -> 27 | C10: =COUNTIFS('Lead Log'!$A:$A,A10,'Lead Log'!$K:$K,"Yes") -> 25 | D10: =IFERROR(C10/B10,0) -> 0.92592593 | E10: =IF(C10>=$C$2,"Yes","No") -> Yes
A11: Aug 10 - Aug 15 | B11: =COUNTIF('Lead Log'!$A:$A,A11) -> 31 | C11: =COUNTIFS('Lead Log'!$A:$A,A11,'Lead Log'!$K:$K,"Yes") -> 25 | D11: =IFERROR(C11/B11,0) -> 0.80645161 | E11: =IF(C11>=$C$2,"Yes","No") -> Yes
A12: Aug 17 - Aug 22 | B12: =COUNTIF('Lead Log'!$A:$A,A12) -> 10 | C12: =COUNTIFS('Lead Log'!$A:$A,A12,'Lead Log'!$K:$K,"Yes") -> 1 | D12: =IFERROR(C12/B12,0) -> 0.1 | E12: =IF(C12>=$C$2,"Yes","No") -> No
A13: Aug 24 - Aug 29 | B13: =COUNTIF('Lead Log'!$A:$A,A13) -> 0 | C13: =COUNTIFS('Lead Log'!$A:$A,A13,'Lead Log'!$K:$K,"Yes") -> 0 | D13: =IFERROR(C13/B13,0) -> 0 | E13: =IF(C13>=$C$2,"Yes","No") -> No
A15: Add more weeks by continuing the date pattern down (each row = next Mon-Sat block) — formulas recalculate automatically.
